README.md
setup.py
cogitare/__init__.py
cogitare.egg-info/PKG-INFO
cogitare.egg-info/SOURCES.txt
cogitare.egg-info/dependency_links.txt
cogitare.egg-info/top_level.txt
cogitare/core/__init__.py
cogitare/core/model.py
cogitare/core/plugin_interface.py
cogitare/core/sequential_model.py
cogitare/data/__init__.py
cogitare/data/async_loader.py
cogitare/data/dataholder.py
cogitare/data/dataset.py
cogitare/data/sequential_dataholder.py
cogitare/data/sequential_dataset.py
cogitare/metrics/__init__.py
cogitare/metrics/classification/__init__.py
cogitare/metrics/regression/__init__.py
cogitare/metrics/spatial/__init__.py
cogitare/models/__init__.py
cogitare/models/classic/__init__.py
cogitare/models/classic/feedforward.py
cogitare/models/classic/logistic.py
cogitare/models/graph/__init__.py
cogitare/models/graph/crf.py
cogitare/monitor/__init__.py
cogitare/monitor/monitor.py
cogitare/monitor/workers/__init__.py
cogitare/monitor/workers/basic.py
cogitare/monitor/workers/system_usage.py
cogitare/plugins/__init__.py
cogitare/plugins/early_stopping.py
cogitare/plugins/evaluator.py
cogitare/plugins/logger.py
cogitare/plugins/plotting.py
cogitare/plugins/progress_bar.py
cogitare/utils/__init__.py