Metadata-Version: 1.0
Name: cogitare
Version: 0.1.0
Summary:  Cogitare - A Modern, Powerful, and Modular Deep Learning and Machine Learning framework in Python.
Home-page: https://github.com/cogitare-ai/cogitare
Author: Aron Bordin
Author-email: aron.bordin@gmail.com
License: UNKNOWN
Keywords: deep learning,framework,PyTorch
Platform: UNKNOWN
